[
  {
    "id": 1,
    "question": "じしんがきた。さあどうする？",
    "choices": ["ドアを開ける", "テレビをつける"],
    "answer": "0"
  },
  {
    "id": 2,
    "question": "かじだ！さあどうする？",
    "choices": ["じぶんでがんばってけす", "おおきなこえで まわりのひとをよぶ"],
    "answer": "1"
  },
  {
    "id": 3,
    "question": "ぼうさいの日はいつ？",
    "choices": ["9月1日", "12月1日"],
    "answer": "0"
  },
  {
    "id": 3,
    "question": "旗が岡八幡神社の神殿の前庭に一対の獅子に似た獣の像・狛犬が配置されていますが、口をあけているのはどっち？地図を参考に見に行ってみよう！",
    "rubi": "はたがおかはちまんじんじゃ の しんでんのまえにわ に いっついの ししににた けもののぞう こまいぬが はいちされていますが くちをあけているのはどっち？ ちずをさんこうに みにいってみよう！",
    "choices": ["みぎ", "ひだり"],
    "mapLink": "https://www.google.com/maps/embed?pb=!1m14!1m8!1m3!1d12975.742728275956!2d139.7079289!3d35.6046531!3m2!1i1024!2i768!4f13.1!3m3!1m2!1s0x0%3A0x93f81c9f537d3ce6!2z5peX5bKh5YWr5bmh56We56S-!5e0!3m2!1sja!2sjp!4v1610853811852!5m2!1sja!2sjp",
    "answer": "0"
  }
]
